clients/__init__.py
clients/sharepoint_client.py
icc_utils-0.1.67.dist-info/licenses/LICENSE
utils/__init__.py
utils/exceptions.py
utils/file_utils.py
utils/pandas_utils.py
utils/samsara_utils.py
utils/sql_utils.py
utils/system_utils.py
utils/wrike_utils.py
icc_utils-0.1.67.dist-info/METADATA
icc_utils-0.1.67.dist-info/WHEEL
icc_utils-0.1.67.dist-info/top_level.txt
icc_utils-0.1.67.dist-info/RECORD
